beartest/__init__.py
beartest/beartest.py
beartest-1.0.4.dist-info/LICENSE.txt
beartest-1.0.4.dist-info/METADATA
beartest-1.0.4.dist-info/WHEEL
beartest-1.0.4.dist-info/top_level.txt
beartest-1.0.4.dist-info/RECORD
